utphy_richdocument/__init__.py
utphy_richdocument/admin.py
utphy_richdocument/apps.py
utphy_richdocument/models.py
utphy_richdocument/tests.py
utphy_richdocument/views.py
utphy_richdocument/migrations/__init__.py
utphy_richdocument/static/.DS_Store
utphy_richdocument/static/.sass-cache/509bd8e5329f278204df3af809b978e4b0a2a0d8/_uoft_colors.scssc
utphy_richdocument/static/.sass-cache/509bd8e5329f278204df3af809b978e4b0a2a0d8/utphy_streamdoc.scssc
utphy_richdocument/static/.sass-cache/9f463901883ffa3a1e9819733805223324da498c/_uoft_colors.scssc
utphy_richdocument/static/.sass-cache/9f463901883ffa3a1e9819733805223324da498c/utphy_richdocument.scssc
utphy_richdocument/static/css/_uoft_colors.scss
utphy_richdocument/static/css/utphy_richdocument.css
utphy_richdocument/static/css/utphy_richdocument.css.map
utphy_richdocument/static/css/utphy_richdocument.scss
utphy_richdocument/static/scss/_uoft_colors.scss
utphy_richdocument/static/scss/utphy_richdocument.scss
utphy_richdocument/templates/utphy_richdocument/base_utphy_richdocument.html
utphy_richdocument/templates/utphy_richdocument/blocks/bustout.html
utphy_richdocument/templates/utphy_richdocument/blocks/code.html
utphy_richdocument/templates/utphy_richdocument/blocks/doc_byline.html
utphy_richdocument/templates/utphy_richdocument/blocks/math.html
utphy_richdocument/templates/utphy_richdocument/blocks/quote.html
utphy_richdocument/templates/utphy_richdocument/blocks/utmedia.html
utphy_richdocument/templates/utphy_richdocument/blocks/video.html
wagtail_utphy_richdocument-0.7.4.dist-info/DESCRIPTION.rst
wagtail_utphy_richdocument-0.7.4.dist-info/METADATA
wagtail_utphy_richdocument-0.7.4.dist-info/RECORD
wagtail_utphy_richdocument-0.7.4.dist-info/WHEEL
wagtail_utphy_richdocument-0.7.4.dist-info/metadata.json
wagtail_utphy_richdocument-0.7.4.dist-info/top_level.txt
