Metadata-Version: 2.0
Name: wagtail-utphy-richdocument
Version: 0.7.4
Summary: A Wagtail richdocument content type built with wagtail streamfield.
Home-page: https://github.com/jcuotpc/wagtail-utphy-richdocument
Author: Julian Comanean
Author-email: icom@physics.utoronto.ca
License: BSD License
Keywords: wagtail,richdocument
Platform: UNKNOWN
Classifier: Environment :: Web Environment
Classifier: Framework :: Django
Classifier: Intended Audience :: Developers
Classifier: License :: OSI Approved :: BSD License
Classifier: Operating System :: OS Independent
Classifier: Programming Language :: Python
Classifier: Programming Language :: Python :: 2.7
Classifier: Programming Language :: Python :: 3
Classifier: Programming Language :: Python :: 3.4
Classifier: Programming Language :: Python :: 3.5
Classifier: Topic :: Internet :: WWW/HTTP
Classifier: Topic :: Internet :: WWW/HTTP :: Dynamic Content
